gmprocess/__init__.py
gmprocess/apps/__init__.py
gmprocess/apps/gmrecords.py
gmprocess/bin/__init__.py
gmprocess/bin/bundle_datarelease.py
gmprocess/bin/cwa_gather.py
gmprocess/bin/fetch_orfeus.py
gmprocess/bin/fix_inventory.py
gmprocess/bin/gmconvert.py
gmprocess/bin/gminfo.py
gmprocess/bin/gmprocess_config.py
gmprocess/bin/gmrecords.py
gmprocess/bin/gmworkspace.py
gmprocess/bin/update_event_json.sh
gmprocess/core/__init__.py
gmprocess/core/provenance.py
gmprocess/core/scalar_event.py
gmprocess/core/stationstream.py
gmprocess/core/stationtrace.py
gmprocess/core/streamarray.py
gmprocess/core/streamcollection.py
gmprocess/data/CESMD_NGA_ids.csv
gmprocess/data/__init__.py
gmprocess/data/config_production.yml
gmprocess/data/config_production_v1.yml
gmprocess/data/config_test.yml
gmprocess/data/config_test_download.yml
gmprocess/data/cosmos_table10.xls
gmprocess/data/cosmos_table4.xls
gmprocess/data/fdsn_codes.csv
gmprocess/data/modules.yml
gmprocess/data/nga_w2_selected.csv
gmprocess/data/picker.yml
gmprocess/data/station_coordinates.xlsx
gmprocess/data/usgs_ids_nga_and_srcmod_cross_reference.xlsx
gmprocess/data/demo/ci38457511/raw/CICCC.RAW
gmprocess/data/demo/ci38457511/raw/CICLC.v1
gmprocess/data/demo/ci38457511/raw/CITOW2.RAW
gmprocess/data/demo/nc72282711/workspace.h5
gmprocess/data/lme/SA_rotd50.0_2020.03.31.csv
gmprocess/data/nn_clipping/bias_1.csv
gmprocess/data/nn_clipping/bias_output.csv
gmprocess/data/nn_clipping/masterF.txt
gmprocess/data/nn_clipping/weight_1.csv
gmprocess/data/nn_clipping/weight_output.csv
gmprocess/data/nn_qa/Cant/M.csv
gmprocess/data/nn_qa/Cant/bias_1.csv
gmprocess/data/nn_qa/Cant/bias_2.csv
gmprocess/data/nn_qa/Cant/bias_output.csv
gmprocess/data/nn_qa/Cant/final_training.csv
gmprocess/data/nn_qa/Cant/masterF.txt
gmprocess/data/nn_qa/Cant/model_3.txt
gmprocess/data/nn_qa/Cant/model_5.txt
gmprocess/data/nn_qa/Cant/mu_sigma.csv
gmprocess/data/nn_qa/Cant/weight_1.csv
gmprocess/data/nn_qa/Cant/weight_2.csv
gmprocess-2.5.0.dist-info/licenses/LICENSE.md
gmprocess-2.5.0.dist-info/METADATA
gmprocess-2.5.0.dist-info/WHEEL
gmprocess-2.5.0.dist-info/entry_points.txt
gmprocess-2.5.0.dist-info/top_level.txt
gmprocess-2.5.0.dist-info/RECORD
