Metadata-Version: 2.4
Name: gmprocess
Version: 2.5.0
Summary: USGS Automated Ground Motion Processing Software
Author-email: Eric Thompson <emthompsone@usgs.gov>, Mike Hearne <mhearne@usgs.gov>, Brad Aagaard <baagaard@usgs.gov>, Bruce Worden <cbworden@contractor.usgs.gov>, John Rekoske <jrekoske@ucsd.edu>, Heather Hunsinger <hhunsinger@usgs.gov>, Gabe Ferragut <gferragut@usgs.gov>
License: License
Requires-Python: >=3.9
License-File: LICENSE.md
Requires-Dist: beautifulsoup4>=4.11.0
Requires-Dist: configobj>=5.0.6
Requires-Dist: esi-core>=1.0.1
Requires-Dist: esi-utils-colors>1.0
Requires-Dist: esi-utils-io>1.0
Requires-Dist: esi-utils-rupture<=1.0.4,>1.0
Requires-Dist: folium>=0.12
Requires-Dist: gmpacket>=0.1.6
Requires-Dist: h5py>=3.11
Requires-Dist: lxml>=4.6.1
Requires-Dist: matplotlib>=3.1.0
Requires-Dist: numba>=0.58
Requires-Dist: numpy<2.0,>=1.21
Requires-Dist: obspy>=1.4.1
Requires-Dist: openpyxl>=3.0.8
Requires-Dist: openquake.engine>=3.18
Requires-Dist: pandas>=1.0
Requires-Dist: Pint>0.24.3
Requires-Dist: ps2ff>=1.5.2
Requires-Dist: pyasdf>=0.7
Requires-Dist: pydantic>=2.0
Requires-Dist: requests>=2.29
Requires-Dist: ruamel.yaml>=0.17.16
Requires-Dist: schema>=0.7
Requires-Dist: scipy>=1.7
Requires-Dist: setuptools-scm>=6.3.2
Requires-Dist: statsmodels>=0.12.2
Requires-Dist: tqdm>4.67
Requires-Dist: usgs-strec>=2.3.11
Requires-Dist: xlrd>=2.0
Provides-Extra: dev
Requires-Dist: build>=0.7.0; extra == "dev"
Requires-Dist: black>=21; extra == "dev"
Requires-Dist: esi-releases>=0.1; extra == "dev"
Requires-Dist: flake8>=3.9; extra == "dev"
Requires-Dist: ipython>=7.26; extra == "dev"
Requires-Dist: pylint>=2.17; extra == "dev"
Provides-Extra: test
Requires-Dist: pytest>=6.2; extra == "test"
Requires-Dist: pytest-cov>=2.12; extra == "test"
Requires-Dist: pytest-console-scripts>=1.4; extra == "test"
Requires-Dist: vcrpy>=4.1; extra == "test"
Provides-Extra: doc
Requires-Dist: altair>=4.2.2; extra == "doc"
Requires-Dist: furo>=2023.3.27; extra == "doc"
Requires-Dist: myst-nb>=0.17.2; extra == "doc"
Requires-Dist: myst-parser>=0.18.1; extra == "doc"
Requires-Dist: nbsphinx>=0.9.1; extra == "doc"
Requires-Dist: recommonmark>=0.7.1; extra == "doc"
Requires-Dist: sphinx>5.0.0; extra == "doc"
Requires-Dist: sphinx-autoapi<3.0.0; extra == "doc"
Requires-Dist: sphinx-copybutton>=0.5.2; extra == "doc"
Requires-Dist: sphinx-inline-tabs>=2023.4.21; extra == "doc"
Requires-Dist: sphinxcontrib-programoutput>=0.17; extra == "doc"
Provides-Extra: build
Requires-Dist: build; extra == "build"
Requires-Dist: twine; extra == "build"
Requires-Dist: check-wheel-contents; extra == "build"
Dynamic: license-file
